sniffkit/__init__.py
sniffkit/cli.py
sniffkit/core.py
sniffkit/okru.py
sniffkit-0.2.1.dist-info/METADATA
sniffkit-0.2.1.dist-info/WHEEL
sniffkit-0.2.1.dist-info/entry_points.txt
sniffkit-0.2.1.dist-info/top_level.txt
sniffkit-0.2.1.dist-info/RECORD
