Metadata-Version: 2.4
Name: sniffkit
Version: 0.2.1
Summary: Selenium performance-log stream sniffer (m3u8)
Requires-Python: >=3.11
Requires-Dist: selenium>=4.10
